setup.py
django_scanredirect.egg-info/PKG-INFO
django_scanredirect.egg-info/SOURCES.txt
django_scanredirect.egg-info/dependency_links.txt
django_scanredirect.egg-info/not-zip-safe
django_scanredirect.egg-info/top_level.txt
scanredirect/__init__.py
scanredirect/urls.py
scanredirect/views.py